pygments_lexer_obsidian/__init__.py
pygments_lexer_obsidian/lexer.py
pygments_lexer_obsidian-0.1.2.dist-info/LICENSE.txt
pygments_lexer_obsidian-0.1.2.dist-info/LICENSE.txt~
pygments_lexer_obsidian-0.1.2.dist-info/METADATA
pygments_lexer_obsidian-0.1.2.dist-info/WHEEL
pygments_lexer_obsidian-0.1.2.dist-info/entry_points.txt
pygments_lexer_obsidian-0.1.2.dist-info/top_level.txt
pygments_lexer_obsidian-0.1.2.dist-info/RECORD
